odc/geo/__init__.py
odc/geo/_blocks.py
odc/geo/_compress.py
odc/geo/_dask.py
odc/geo/_interop.py
odc/geo/_map.py
odc/geo/_rgba.py
odc/geo/_version.py
odc/geo/_xr_interop.py
odc/geo/converters.py
odc/geo/crs.py
odc/geo/gcp.py
odc/geo/geobox.py
odc/geo/geom.py
odc/geo/gridspec.py
odc/geo/math.py
odc/geo/overlap.py
odc/geo/py.typed
odc/geo/roi.py
odc/geo/testutils.py
odc/geo/types.py
odc/geo/ui.py
odc/geo/warp.py
odc/geo/xr.py
odc/geo/cog/__init__.py
odc/geo/cog/_az.py
odc/geo/cog/_mpu.py
odc/geo/cog/_mpu_fs.py
odc/geo/cog/_multipart.py
odc/geo/cog/_rio.py
odc/geo/cog/_s3.py
odc/geo/cog/_shared.py
odc/geo/cog/_tifffile.py
odc/geo/data/__init__.py
odc/geo/data/gbox.css
odc/geo/data/ocean.geojson.xz
odc_geo-0.4.9.dist-info/LICENSE
odc_geo-0.4.9.dist-info/METADATA
odc_geo-0.4.9.dist-info/WHEEL
odc_geo-0.4.9.dist-info/top_level.txt
odc_geo-0.4.9.dist-info/RECORD
