Metadata-Version: 2.2
Name: odc-geo
Version: 0.4.9
Summary: Geometry Classes and Operations (opendatacube)
Home-page: https://github.com/opendatacube/odc-geo/
Author: Open Data Cube
Author-email: 
Maintainer: Open Data Cube
Maintainer-email: 
License: Apache License 2.0
Project-URL: Documentation, https://odc-geo.readthedocs.io/en/latest/
Project-URL: Bug Reporting, https://github.com/opendatacube/odc-geo/issues
Platform: any
Classifier: License :: OSI Approved :: Apache Software License
Classifier: Intended Audience :: Developers
Classifier: Operating System :: OS Independent
Classifier: Programming Language :: Python :: 3.8
Classifier: Programming Language :: Python :: 3.9
Classifier: Topic :: Software Development :: Libraries :: Python Modules
Classifier: Topic :: Scientific/Engineering :: GIS
Classifier: Typing :: Typed
Requires-Python: >=3.8
License-File: LICENSE
Requires-Dist: affine
Requires-Dist: cachetools
Requires-Dist: numpy
Requires-Dist: pyproj>=3.0.0
Requires-Dist: shapely
Provides-Extra: xr
Requires-Dist: xarray>=0.19; extra == "xr"
Provides-Extra: warp
Requires-Dist: rasterio; extra == "warp"
Provides-Extra: tiff
Requires-Dist: tifffile; extra == "tiff"
Requires-Dist: imagecodecs; extra == "tiff"
Requires-Dist: dask[array,distributed]; extra == "tiff"
Requires-Dist: rasterio; extra == "tiff"
Requires-Dist: xarray>=0.19; extra == "tiff"
Provides-Extra: s3
Requires-Dist: boto3; extra == "s3"
Provides-Extra: az
Requires-Dist: azure-storage-blob; extra == "az"
Provides-Extra: all
Requires-Dist: rasterio; extra == "all"
Requires-Dist: tifffile; extra == "all"
Requires-Dist: imagecodecs; extra == "all"
Requires-Dist: dask[array,distributed]; extra == "all"
Requires-Dist: rasterio; extra == "all"
Requires-Dist: xarray>=0.19; extra == "all"
Requires-Dist: boto3; extra == "all"
Requires-Dist: azure-storage-blob; extra == "all"
Provides-Extra: test
Requires-Dist: pytest; extra == "test"
Requires-Dist: geopandas; extra == "test"
Requires-Dist: tifffile; extra == "test"
Requires-Dist: imagecodecs; extra == "test"
Requires-Dist: dask[array,distributed]; extra == "test"
Requires-Dist: rasterio; extra == "test"
Requires-Dist: xarray>=0.19; extra == "test"
